odoo/addons/purchase_request_product_usage/README.rst
odoo/addons/purchase_request_product_usage/__init__.py
odoo/addons/purchase_request_product_usage/__manifest__.py
odoo/addons/purchase_request_product_usage/i18n/nl_NL.po
odoo/addons/purchase_request_product_usage/i18n/purchase_request_product_usage.pot
odoo/addons/purchase_request_product_usage/models/__init__.py
odoo/addons/purchase_request_product_usage/models/purchase_request.py
odoo/addons/purchase_request_product_usage/readme/CONTRIBUTORS.rst
odoo/addons/purchase_request_product_usage/readme/DESCRIPTION.rst
odoo/addons/purchase_request_product_usage/readme/USAGE.rst
odoo/addons/purchase_request_product_usage/security/ir.model.access.csv
odoo/addons/purchase_request_product_usage/static/description/icon.png
odoo/addons/purchase_request_product_usage/static/description/index.html
odoo/addons/purchase_request_product_usage/tests/__init__.py
odoo/addons/purchase_request_product_usage/tests/test_purchase_request_product_usage.py
odoo/addons/purchase_request_product_usage/views/purchase_request_view.xml
odoo/addons/purchase_request_product_usage/wizards/__init__.py
odoo/addons/purchase_request_product_usage/wizards/purchase_request_line_make_purchase_order.py
odoo/addons/purchase_request_product_usage/wizards/purchase_request_line_make_purchase_order_view.xml
odoo12_addon_purchase_request_product_usage-12.0.1.0.0.99.dev4.dist-info/METADATA
odoo12_addon_purchase_request_product_usage-12.0.1.0.0.99.dev4.dist-info/WHEEL
odoo12_addon_purchase_request_product_usage-12.0.1.0.0.99.dev4.dist-info/top_level.txt
odoo12_addon_purchase_request_product_usage-12.0.1.0.0.99.dev4.dist-info/RECORD
